flowai_sdk/__init__.py
flowai_sdk/_hooks/__init__.py
flowai_sdk/_hooks/registration.py
flowai_sdk/_hooks/sdkhooks.py
flowai_sdk/_hooks/types.py
flowai_sdk/_version.py
flowai_sdk/apikeys.py
flowai_sdk/authentication.py
flowai_sdk/basesdk.py
flowai_sdk/batches.py
flowai_sdk/clerk_webhooks.py
flowai_sdk/datasets.py
flowai_sdk/errors/__init__.py
flowai_sdk/errors/apierror.py
flowai_sdk/errors/httpvalidationerror.py
flowai_sdk/health.py
flowai_sdk/httpclient.py
flowai_sdk/integrations.py
flowai_sdk/jobs.py
flowai_sdk/models/__init__.py
flowai_sdk/models/add_project_validator_projects_project_id_validators_postop.py
flowai_sdk/models/apikeycreate.py
flowai_sdk/models/apikeycreateresponse.py
flowai_sdk/models/apikeyinfo.py
flowai_sdk/models/apikeyupdate.py
flowai_sdk/models/archive_project_projects_project_id_archive_postop.py
flowai_sdk/models/batchread.py
flowai_sdk/models/batchstatusread.py
flowai_sdk/models/body_create_stages_for_project_stages_post.py
flowai_sdk/models/body_update_test_case_test_cases_test_case_id_put.py
flowai_sdk/models/cancel_job_by_id_jobs_job_id_cancel_postop.py
flowai_sdk/models/check_validation_task_status_validation_tasks_validation_task_id_getop.py
flowai_sdk/models/create_job_for_project_projects_project_id_jobs_postop.py
flowai_sdk/models/create_test_case_test_cases_postop.py
flowai_sdk/models/create_test_case_validation_validations_postop.py
flowai_sdk/models/create_validation_task_for_batch_endpoint_batches_batch_id_validation_tasks_postop.py
flowai_sdk/models/createvalidationtaskresponse.py
flowai_sdk/models/datasetgenerationrequest.py
flowai_sdk/models/datasetitemlistresponse.py
flowai_sdk/models/datasetitemread.py
flowai_sdk/models/datasetread.py
flowai_sdk/models/delete_batch_by_id_batches_batch_id_deleteop.py
flowai_sdk/models/delete_dataset_datasets_dataset_id_deleteop.py
flowai_sdk/models/delete_project_projects_project_id_deleteop.py
flowai_sdk/models/delete_stage_stages_stage_id_deleteop.py
flowai_sdk-0.1.8.dist-info/METADATA
flowai_sdk-0.1.8.dist-info/WHEEL
flowai_sdk-0.1.8.dist-info/RECORD
